{
  "schema": {
    "type": 2,
    "typeName": ""
  },
  "id": 23,
  "title": {
    "arabic": "اَلدُّعَاءُ عِنْدَ خِتَامِ الْمَجَالِسِ",
    "latin": "Doa Penutup Majelis"
  },
  "content": [
    "لاَ اِلٰهَ اِلَّا اللّٰهُ ۳× ۞ مُحَمَّدٌرَسُولُ اللّٰهِ",
    "يَا رَبَّنَا اعْتَرَفْنَا ۞ بِاَنَّنَا اقْتَرَفْنَا",
    "وَاَنَّنَا اَسْرَفْنَا ۞ عَلَى لَظٰى اَسْرَفْنَا",
    "فَتُبْ عَلَيْنَا تَوْبَةً ۞ تَغْسِلْ لِكُلِّ حَوْبَةْ",
    "وَاسْتُرْلَنَا الْعَوْرَاتِ ۞ وَاٰمِنِ الرَّوْعَاتِ",
    "وَاغْفِرْ لِوَالِدِيْنَا ۞ رَبِّ وَمَوْلُوْدِيْنَا",
    "وَالْآلِ وَالْاِخْوَانِ ۞ وَسَائِرِ الْخِلَّانِ",
    "وَكُلِّ ذِيْ مَحَبَّةْ ۞ اَوْجِيْرَةٍ اَوْصُحْبَةْ",
    "وَالْمُسْلِمِيْنَ اجْمَعْ ۞ اٰمِيْنَ رَبِّ اسْمَعْ",
    "فَضْلًا وَجُودًا مَنَّا ۞ لَابِاكْتِسَابٍ مِنَّا",
    "بِالْمُصْطَفٰى الرَّسُوْلِ ۞ نَحْظٰى بِكُلِّ سُوْلِ",
    "صَلَّى وَسَلَّمْ رَبِّى ۞ عَلَيْهِ عَدَّالْحَبِّ",
    "وَاٰلِهِ والصَّحْبِ ۞ عَدَدَطَشِّ السُّحْبِ",
    "وَالَحَمْدُ لِلْاِلٰهِ ۞ فِيْ الْبَدْءِ وَالتَّنَاهِىْ"
  ]
}
