{
  "schema": {
    "type": 3,
    "typeName": ""
  },
  "id": 5,
  "title": {
    "arabic": "مَنْظُوْمَاتُ الْأَسْمَاءِ الْحُسْنٰى",
    "latin": "Mandhumat Asmaul Husna"
  },
  "content": [
    [
      "بِسْمِ الْإِلٰهِ وَبِهٖ بَدَأْنَا",
      "وَلَوْ عَبَدْنَا غَيْرَهُ لَشَقِيْنَا"
    ],
    ["يَا حَبَّذَا رَبًّا وَّحُبَّ دِيْنَا", "وَحَبَّذَا مُحَمَّدٌ هَادِيْنَا"],
    "لَوْلَاهُ مَا كُنَّا وَلَا بَقِيْنَا",
    [
      "اَللّٰهُ لَوْلَا أَنْتَ مَا اهْتَدَيْنَا",
      "وَلَا تَصَدَّقْنَا وَلَا صَلَّيْنَا"
    ],
    [
      "فَأَنْزِلَنْ سَكِينَةً عَلَيْنَا",
      "وَثَبِّتِ الْأَقْدَامَ إِنْ لَا قَيْنَا"
    ],
    "نَحْنُ الْأُوْلٰى جَاؤُكَ مُسْلِمِيْنَ",
    [
      "وَالْمُشْرِكُوْنَ قَدْ بَغَوْا عَلَيْنَا",
      "إِذَا أَرَادُوْا فِتْنَةً اَبَيْنَا"
    ],
    [
      "وَقَدْ تَدَاعٰى جَمْعُهُمْ عَلَيْنَا",
      "طِبْقَ الْأَحَادِيْثِ الّٰتِي رَوَيْنَا"
    ],
    "فَارُدُدْهُمُ اللّٰهُمَّ خَاسِرِيْنَ",
    [
      "اَللّٰهُ يَا رَحْمٰنُ يَا رَحِيْمُ",
      "اَللّٰهُ يَا حَيُّ وَيَا قَيُّوْمُ"
    ],
    ["اَللّٰهُ يَا قَوِيُّ يَا قَدِيْمُ", "اَللّٰهُ يَا عَلِيُّ يَا عَظِيْمُ"],
    "لَا يَنْبَغِيْ لِلْقَوْمِ أَنْ يَّعْلُوْنَا",
    ["اَللّٰهُ يَا لَطِيْفُ يَا عَلِيْمُ", "اَللّٰهُ يَا رَؤٗفُ يَا حَكِيْمُ"],
    [
      "اَللّٰهُ يَا تَوَّابُ يَا حَلِيْمُ",
      "اَللّٰهُ يَا وَهَّابُ يَا كَرِيْمُ"
    ],
    "هَبْنَا الْعُلٰى وَاجْعَلْ عِدَانَا الدُّوْنَا",
    ["اَللّٰهُ يَا مَالِكُ يَا مُنِيْرُ", "اَللّٰهُ يَا مَلِيْكُ يَا قَدِيْرُ"],
    [
      "اَللّٰهُ يَا مَوْلٰى وَيَا نَصِيْرُ",
      "اَللّٰهُ أَنْتَ الْمَلِكُ الْكَبِيْرُ"
    ],
    "لَيْسَ عِدَانَا لَكَ مُعْجِزِيْنَا",
    ["اَللّٰهُ يَا شَاكِرُ يَا شَكُوْرُ", "اَللّٰهُ يَا عَفُوُّ يَا غَفُوْرُ"],
    ["اَللّٰهُ يَا عَالِمُ يَا خَبِيْرُ", "اَللّٰهُ يَا فَتَّاحُ يَا بَصِيْرُ"],
    "لَا تَحْرِمَنَّ فَتْحَكَ الْمُبِيْنَ",
    ["اَللّٰهُ يَا ظَاهِرُ يَا جَلِيْلُ", "اَللّٰهُ يَا بَاطِنُ يَا وَكِيْلُ"],
    ["اَللّٰهُ يَا صَادِقُ يَا جَمِيْلُ", "اَللّٰهُ يَا حَافِظُ يَا كَفِيْلُ"],
    "كُنْ حَافِظًا لَنَا وَكُنْ مُعِيْنَا",
    ["اَللّٰهُ يَاغَنِيُّ يَاحَمِيْدُ", "اَللّٰهُ يَامُغْنِيْ وَيَارَشِيْدُ"],
    [
      "اَللّٰهُ يَا مُبْدِئُ يَا مُعِيْدُ",
      "اَللّٰهُ يَا عَزِيْزُ يَا مَجِيْدُ"
    ],
    "لِعِزِّكَ التَّوْحِيْدِ يَشْكُوْ الْهُوْنَا",
    [
      "اَللّٰهُ يَا قَادِرُ يَا مُقْتَدِرُ",
      "اَللّٰهُ يَا قَاهِرُ يَا مُؤَخِّرُ"
    ],
    [
      "اَللّٰهُ يَا فَاطِرُ يَا مُصَوِّرُ",
      "اَللّٰهُ يَا مُحْصٖى وَيَا مُدَبِّرُ"
    ],
    "دَبِّرْ لَنَا وَدَمِّرِ الْعَادِيْنَا",
    ["اَللّٰهُ يَا دَائِمُ لَا يَمُوْتُ", "اَللّٰهُ يَا قَائِمُ لَا يَفُوْتُ"],
    [
      "اَللّٰهُ يَا مُحْيٖي وَيَا مُمِيْتُ",
      "اَللّٰهُ يَا مُغِيْثُ يَا مُقِيْتُ"
    ],
    "كُنْ غَوْثَنَا وَحِصْنَنَا الْحَصِيْنَا",
    [
      "اَللّٰهُ يَا بَاسِطُ اَنْتَ الْوَاسِعُ",
      "اَللّٰهُ يَا قَابِضُ أَنْتَ الْمَانِعُ"
    ],
    [
      "اَللّٰهُ يَا خَالِقُ أَنْتَ الْجَامِعُ",
      "اَللّٰهُ يَا خَافِضُ أَنتَ الرَّافِعُ"
    ],
    "اِرْفَعْ مَعَالِيْنَا لِعِلِّيِّيْنَا",
    [
      "اَللّٰهُ ذُوْ الْمَعَارِجِ الرَّفِيْعُ",
      "اَللّٰهُ يَا وَافِي وَيَا سَرِيْعُ"
    ],
    [
      "اَللّٰهُ يَا كَافِيْ وَيَا سَمِيْعُ",
      "يَا نُوْرُ يَا هَادِيْ وَيَا بَدِيْعُ"
    ],
    "اَدَّبْتَنَا بِمَا جَرٰى يَكْفِيْنَا",
    [
      "اَللّٰهُ ذُوْ الْجَلَالِ وَالْإِكْرَامِ",
      "اَللّٰهُ ذُوْ الطَّوْلِ عَلَى الدَّوَامِ"
    ],
    [
      "اَللّٰهُ يَا ذَا الْفَضْلِ وَالْإِنْعَامِ",
      "وَالسَّيِّدُ الْمُطْلَقِ لِلْأَنَامِ"
    ],
    "اِرْحَمْ عَبِيْدًا لَّكَ عَابِدِيْنَا",
    [
      "اَللّٰهُ يَا أَوَّلُ اَنْتَ الْوَاحِدُ",
      "اَللّٰهُ يَا اٰخِرَ اَنْتَ الرَّاشِدُ"
    ],
    [
      "يَا وِتْرُ يَا مُتَكَبِّرُ يَا وَاجِدُ",
      "يَا بَرُّيَا مُتَفَصِّلُ يَا مَاجِدُ"
    ],
    "بِفَضْلِكَ اقْبَلْنَا عَلٰى مَا فِيْنَا",
    [
      "اَللّٰهُ يَا مُبِيْنُ يَا وَدُوْدُ",
      "اَللّٰهُ يَا مُحِيْطُ يَا شَهِيْدُ"
    ],
    [
      "اَللّٰهُ يَا مَتِيْنَ يَا شَدِيْدُ",
      "يَا مَنْ هُوَ الْفَعَّالُ مَا يُرِيْدُ"
    ],
    "اِنَّا ضِعَافٌ لَكَ قَدْ لَجَأْنَا",
    [
      "اَللّٰهُ يَا مُعِزُّ يَا مُقَدِّمُ",
      "اَللّٰهُ يَا مُذِلُّ يَا مُنْتَقِمُ"
    ],
    [
      "اَلْبَادِئُ الْبَاقِى فَلَا يَنْعَدِمُ",
      "اَلْمُحْصِنُ الْوَالِى الْحَفِيْظُ الْأَكْرَمُ"
    ],
    "لَيْسَ لَنَا سِوَاكَ مَنْ يَّحْمِيْنَا",
    [
      "اَللّٰهُ يَا وَارِثُ أَنْتَ الْاَبَدُ",
      "اَللّٰهُ يَا بَاعِثُ أَنْتَ الْأَحَدُ"
    ],
    [
      "يَا مَالِكَ الْمُلْكِ الْإِلٰهُ الصَّمَدُ",
      "لَا كُفُؤٌ لَا وَالِدٌ لَا وَلَدُ"
    ],
    "كُفَّ الْعِدَا عَنَّا فَقَدْ أُوْذِيْنَا",
    [
      "اَللّٰهُ يَا غَالِبُ يَا قَهَّارُ",
      "اَللّٰهُ يَا نَافِعُ اَنْتَ الضَّارُّ"
    ],
    [
      "اَللّٰهُ يَا بَارِئُ يَا غَفَّارُ",
      "يَا رَبِّ يَا ذَا الْقُوَّةِ الْجَبَّارُ"
    ],
    "قَوِّمْ لَنَا الدُّنْيَا وَقَوِّ الدِّيْنَ",
    [
      "اَللّٰهُ رَبُّ الْعِزَّةِ السَّلَامُ",
      "اَلْمُؤْمِنُ الْمُهَيْمِنُ العَلَّامُ"
    ],
    [
      "ذُوْ الرَّحْمَةِ الْأَعْلٰى الْأَعَزُّ التَّامُّ",
      "مَنْ دِيْنُهُ الْحَقُّ هُوَ الْإِسْلَامُ"
    ],
    "قَيِّضْ لَهُ اللّٰهُمَّ نَاصِرِيْنَا",
    [
      "اَللّٰهُ أَنْتَ الْمُتَعَالِى الْحَكَمُ",
      "الْفَرْدُ ذُوْ الْعَرْشِ الْوَلِىُّ الْأَحْكَمُ"
    ],
    [
      "اَلْغَافِرُ الْمُعْطِى الْجَوَّادُ الْمُنْعِمُ",
      "اَلْعَادِلُ الْعَدْلُ الصَّبُوْرُ الْأَرْحَمُ"
    ],
    "مَكِّنْ لَّنَا فِي اَرْضِيْنَا تَمْكِيْنَا",
    [
      "اَللّٰهُ يَا قُدُّوْسُ يَا بُرْهَانُ",
      "يَا بَارُّ يَا حَنَّانُ يَا مَنَّانُ"
    ],
    [
      "يَا حَقُّ يَا مُقْسِطُ يَا دَيَّانُ",
      "تَبَارَكَتْ أَسْمَاءُكَ الْحِسَانُ"
    ],
    "بِهَا قَرَعْنَا بَابَكَ الْمَصُوْنَا",
    [
      "اَللّٰهُ يَا خَلَّاقُ يَا مُجِيْبُ",
      "اَللّٰهُ يَا رَزَّاقُ يَا حَسِيْبُ"
    ],
    [
      "اَللّٰهُ يَا قَرِيْبُ يَا رَقِيْبُ",
      "اَللْمُسْتَعَانُ السَّامِعُ الْمُجِيْبُ"
    ],
    "إِنَّا دَعَوْنَاكَ اسْتَجِبْ أَمِيْنَا",
    "وصلّى اللّه على سيّدنا محمّد وعلى اله وصحبه وسلّم"
  ]
}
