{
  "schema": {
    "type": 1,
    "typeName": ""
  },
  "id": 62,
  "title": {
    "arabic": "لَفْظُ تَكْبِيْرِ لِلْعِيْدَيْنِ",
    "latin": "Lafadz Takbir Aidain"
  },
  "content": "اَللّٰهُ أَكْبَرُ ٣× لَآ إِلٰهَ إِلَّا اللّٰهُ، وَاللّٰهُ أَكْبَرُ ، اَللّٰهُ أَكْبَرُ وَلِلّٰهِ الْحَمْدُ. اَللّٰهُ أَكْبَرُ كَبِيْرًا، وَ الْحَمْدُ لِلّٰهِ كَثِيْرًا وَسُبْحَانَ اللّٰهِ بُكْرَةً وَّأَصِيْلًا ، لَآ إِلٰهَ إِلَّا اللّٰهُ وَحْدَهُ ، صَدَقَ وَعْدَهُ، وَنَصَرَ عَبْدَهُ ، وَأَعَزَّ جُنْدَهُ وَهَزَمَ الْأَحْزَابَ وَحْدَهُ ، لَآ إِلٰهَ إِلَّا اللّٰهُ وَلَا نَعْبُدُ اِلَّا إِيَّاهُ مُخْلِصِيْنَ لَهُ الدِّيْنُ، وَلَوْ كَرِهَ الْكَافِرُوْنَ، لَآ إِلٰهَ إِلَّا اللّٰهُ وَاللّٰهُ أَكْبَرُ، اَللّٰهُ أَكْبَرُ وَلِلّٰهِ الْحَمْدُ."
}
